django_signal_manager/__init__.py
django_signal_manager/managers.py
django_signal_manager-0.1.6.dist-info/licenses/LICENSE
django_signal_manager-0.1.6.dist-info/METADATA
django_signal_manager-0.1.6.dist-info/WHEEL
django_signal_manager-0.1.6.dist-info/top_level.txt
django_signal_manager-0.1.6.dist-info/RECORD
